CHANGES.rst
MANIFEST.in
README.rst
setup.cfg
setup.py
thriftpy/__init__.py
thriftpy/_compat.py
thriftpy/hook.py
thriftpy/rpc.py
thriftpy/server.py
thriftpy/thrift.py
thriftpy/tornado.py
thriftpy/utils.py
thriftpy.egg-info/PKG-INFO
thriftpy.egg-info/SOURCES.txt
thriftpy.egg-info/dependency_links.txt
thriftpy.egg-info/not-zip-safe
thriftpy.egg-info/requires.txt
thriftpy.egg-info/top_level.txt
thriftpy/contrib/__init__.py
thriftpy/contrib/tracking/__init__.py
thriftpy/contrib/tracking/tracker.py
thriftpy/contrib/tracking/tracking.thrift
thriftpy/parser/__init__.py
thriftpy/parser/exc.py
thriftpy/parser/lexer.py
thriftpy/parser/parser.py
thriftpy/protocol/__init__.py
thriftpy/protocol/binary.py
thriftpy/protocol/exc.py
thriftpy/protocol/json.py
thriftpy/protocol/multiplex.py
thriftpy/protocol/cybin/cybin.c
thriftpy/protocol/cybin/cybin.pyx
thriftpy/protocol/cybin/endian_port.h
thriftpy/transport/__init__.py
thriftpy/transport/_ssl.py
thriftpy/transport/cybase.c
thriftpy/transport/cybase.pxd
thriftpy/transport/cybase.pyx
thriftpy/transport/socket.py
thriftpy/transport/sslsocket.py
thriftpy/transport/buffered/__init__.py
thriftpy/transport/buffered/cybuffered.c
thriftpy/transport/buffered/cybuffered.pyx
thriftpy/transport/framed/__init__.py
thriftpy/transport/framed/cyframed.c
thriftpy/transport/framed/cyframed.pyx
thriftpy/transport/memory/__init__.py
thriftpy/transport/memory/cymemory.c
thriftpy/transport/memory/cymemory.pyx