Metadata-Version: 1.1
Name: thriftpy
Version: 0.3.3
Summary: Pure python implementation of Apache Thrift.
Home-page: https://thriftpy.readthedocs.org/
Author: Lx Yu
Author-email: i@lxyu.net
License: MIT
Keywords: thrift python thriftpy
Platform: UNKNOWN
Classifier: Topic :: Software Development
Classifier: Development Status :: 4 - Beta
Classifier: Intended Audience :: Developers
Classifier: License :: OSI Approved :: MIT License
Classifier: Programming Language :: Python :: 2.6
Classifier: Programming Language :: Python :: 2.7
Classifier: Programming Language :: Python :: 3.3
Classifier: Programming Language :: Python :: 3.4
Classifier: Programming Language :: Python :: 3.5
Classifier: Programming Language :: Python :: Implementation :: CPython
Classifier: Programming Language :: Python :: Implementation :: PyPy
